{
  "teams": [
    {
      "name": "Yae Miko",
      "teamMembers": [
        "Yae Miko",
        "Fischl",
        "Sangonomiya Kokomi",
        "Kaedehara Kazuha"
      ],
      "description": "",
      "id": 23
    },
    {
      "name": "Hu Tao",
      "teamMembers": [
        "Hu Tao",
        "Xingqiu",
        "Albedo",
        "Zhongli"
      ],
      "description": "",
      "id": 24
    },
    {
      "name": "Ganyu",
      "teamMembers": [
        "Ganyu",
        "Shenhe",
        "Sangonomiya Kokomi",
        "Kaedehara Kazuha"
      ],
      "description": "",
      "id": 25
    },
    {
      "name": "Tartaglia",
      "teamMembers": [
        "Tartaglia",
        "Xiangling",
        "Bennett",
        "Kaedehara Kazuha"
      ],
      "description": "",
      "id": 26
    },
    {
      "name": "Raiden",
      "teamMembers": [
        "Raiden Shogun",
        "Kujou Sara",
        "Bennett",
        "Kaedehara Kazuha"
      ],
      "description": "test",
      "id": 27
    },
    {
      "name": "Noelle",
      "teamMembers": [
        "Noelle",
        "Albedo",
        "Bennett",
        "Zhongli"
      ],
      "description": "",
      "id": 28
    }
  ],
  "characters": [
    {
      "name": "Albedo",
      "levelLow": 1,
      "levelHigh": 14,
      "NALow": 1,
      "NAHigh": 10,
      "ESLow": 1,
      "ESHigh": 10,
      "EBLow": 1,
      "EBHigh": 10,
      "moraCharacter": 2092530,
      "moraTalent": 4957500,
      "expBooks": 419,
      "localSpeciality": 168,
      "characterCommonMaterial1": 18,
      "talentCommonMaterial1": 18,
      "characterCommonMaterial2": 30,
      "talentCommonMaterial2": 66,
      "characterCommonMaterial3": 36,
      "talentCommonMaterial3": 93,
      "bossAscensionMaterial": 46,
      "sliver": 1,
      "fragments": 9,
      "chunks": 9,
      "gemstones": 6,
      "bronzeTalentBooks": 9,
      "silverTalentBooks": 63,
      "goldTalentBooks": 114,
      "bossMaterial": 18,
      "crown": 3,
      "id": 7
    },
    {
      "name": "Barbara",
      "levelLow": 1,
      "levelHigh": 12,
      "NALow": 1,
      "NAHigh": 8,
      "ESLow": 1,
      "ESHigh": 8,
      "EBLow": 1,
      "EBHigh": 8,
      "moraCharacter": 1286905,
      "moraTalent": 1507500,
      "expBooks": 247,
      "localSpeciality": 108,
      "characterCommonMaterial1": 18,
      "talentCommonMaterial1": 18,
      "characterCommonMaterial2": 30,
      "talentCommonMaterial2": 66,
      "characterCommonMaterial3": 12,
      "talentCommonMaterial3": 30,
      "bossAscensionMaterial": 26,
      "sliver": 1,
      "fragments": 9,
      "chunks": 9,
      "gemstones": 0,
      "bronzeTalentBooks": 9,
      "silverTalentBooks": 63,
      "goldTalentBooks": 30,
      "bossMaterial": 6,
      "crown": 0,
      "id": 8
    },
    {
      "name": "Kamisato Ayaka",
      "levelLow": 1,
      "levelHigh": 14,
      "NALow": 1,
      "NAHigh": 10,
      "ESLow": 1,
      "ESHigh": 9,
      "EBLow": 1,
      "EBHigh": 10,
      "moraCharacter": 2092530,
      "moraTalent": 4257500,
      "expBooks": 419,
      "localSpeciality": 168,
      "characterCommonMaterial1": 18,
      "talentCommonMaterial1": 18,
      "characterCommonMaterial2": 30,
      "talentCommonMaterial2": 66,
      "characterCommonMaterial3": 36,
      "talentCommonMaterial3": 81,
      "bossAscensionMaterial": 46,
      "sliver": 1,
      "fragments": 9,
      "chunks": 9,
      "gemstones": 6,
      "bronzeTalentBooks": 9,
      "silverTalentBooks": 63,
      "goldTalentBooks": 98,
      "bossMaterial": 16,
      "crown": 2,
      "id": 9
    }
  ]
}